examples/__init__.py
examples/api.py
examples/example_objects.py
examples/registry.py
examples-1.0.1.dist-info/LICENSE
examples-1.0.1.dist-info/WHEEL
examples-1.0.1.dist-info/METADATA
examples-1.0.1.dist-info/RECORD
