Metadata-Version: 2.1
Name: examples
Version: 1.0.1
Summary: Tests and Documentation Done by Example.
License: MIT
Author: Timothy Crosley
Author-email: timothy.crosley@gmail.com
Requires-Python: >=3.6,<4.0
Classifier: License :: OSI Approved :: MIT License
Classifier: Programming Language :: Python :: 3
Classifier: Programming Language :: Python :: 3.6
Classifier: Programming Language :: Python :: 3.7
Requires-Dist: pydantic (>=0.32.2,<0.33.0)
